autopptx/__init__.py
autopptx/Image/__init__.py
autopptx/Image/image.py
autopptx/Image/images.py
autopptx/Image/style.py
autopptx/Table/__init__.py
autopptx/Table/style.py
autopptx/Table/table.py
autopptx/Table/tables.py
autopptx/Text/__init__.py
autopptx/Text/style.py
autopptx/Text/text.py
autopptx/Text/texts.py
autopptx/Type/__init__.py
autopptx/Type/find.py
autopptx/Type/type.py
autopptx/View/__init__.py
autopptx/View/view.py
autopptx/core/__init__.py
autopptx/core/runner.py
autopptx-1.0.0.dist-info/licenses/LICENSE
data/bunny1.png
data/bunny2.png
data/cat1.png
data/input_data.json
data/output_demo.pptx
data/template.pptx
autopptx-1.0.0.dist-info/METADATA
autopptx-1.0.0.dist-info/WHEEL
autopptx-1.0.0.dist-info/top_level.txt
autopptx-1.0.0.dist-info/RECORD
