Metadata-Version: 2.4
Name: autopptx
Version: 1.0.0
Summary: A Python tool for automated editing of PowerPoint templates using python-pptx
Author-email: Chenzhe <chenzhe0_0@163.com>
Maintainer-email: Chenzhe <chenzhe0_0@163.com>
License: MIT
Project-URL: Homepage, https://github.com/chenzhex/AutoPPTX
Project-URL: Documentation, https://github.com/chenzhex/AutoPPTX#readme
Project-URL: Repository, https://github.com/chenzhex/AutoPPTX
Project-URL: Issues, https://github.com/chenzhex/AutoPPTX/issues
Keywords: powerpoint,automation,presentation,python-pptx,template
Classifier: Development Status :: 3 - Alpha
Classifier: Programming Language :: Python :: 3
Classifier: Programming Language :: Python :: 3.10
Classifier: License :: OSI Approved :: MIT License
Classifier: Operating System :: OS Independent
Classifier: Topic :: Software Development :: Libraries
Requires-Python: >=3.10
License-File: LICENSE
Requires-Dist: python-pptx>=1.0.2
Requires-Dist: lxml>=5.3.1
Provides-Extra: dev
Requires-Dist: pytest; extra == "dev"
Requires-Dist: black; extra == "dev"
Requires-Dist: coverage; extra == "dev"
Requires-Dist: build; extra == "dev"
Requires-Dist: twine; extra == "dev"
Dynamic: license-file
